Spelt-0.3.0.dist-info/METADATA
Spelt-0.3.0.dist-info/RECORD
Spelt-0.3.0.dist-info/WHEEL
Spelt-0.3.0.dist-info/entry_points.txt
Spelt-0.3.0.dist-info/top_level.txt
spelt/__init__.py
spelt/picker.py
