Metadata-Version: 2.1
Name: Spelt
Version: 0.3.0
Summary: Spelt is a small python application aimed to allow users to backup their photo from https://vk.com to local storage.
Home-page: https://github.com/amka/spelt
Author: Andrey Maksimov
Author-email: meamka@ya.ru
License: MIT
Platform: UNKNOWN
Classifier: Programming Language :: Python :: 3
Classifier: License :: OSI Approved :: MIT License
Classifier: Operating System :: MacOS
Classifier: Operating System :: POSIX
Requires-Dist: requests (==2.19.1)
Requires-Dist: vk-api (==11.0.0)
